dj_spam-0.2.0.dist-info/DESCRIPTION.rst
dj_spam-0.2.0.dist-info/METADATA
dj_spam-0.2.0.dist-info/metadata.json
dj_spam-0.2.0.dist-info/RECORD
dj_spam-0.2.0.dist-info/top_level.txt
dj_spam-0.2.0.dist-info/WHEEL
spam/__init__.py
spam/admin.py
spam/behaviors.py
spam/exceptions.py
spam/models.py
spam/urls.py
spam/utils.py
spam/views.py
spam/migrations/0001_initial.py
spam/migrations/0002_auto_20150728_2050.py
spam/migrations/__init__.py
spam/static/css/spam.css
spam/static/js/spam.js
spam/templates/spam/base.html
spam/templates/spam/spammyposting_form.html
spam/templates/spam/thanks.html
