Metadata-Version: 2.0
Name: dj-spam
Version: 0.2.0
Summary: Django + Fighting Spam Made Easy
Home-page: https://github.com/pydanny/dj-spam
Author: Daniel Roy Greenfeld
Author-email: pydanny@gmail.com
License: BSD
Keywords: dj-spam
Platform: UNKNOWN
Classifier: Development Status :: 2 - Pre-Alpha
Classifier: Framework :: Django
Classifier: Framework :: Django :: 1.8
Classifier: Intended Audience :: Developers
Classifier: License :: OSI Approved :: BSD License
Classifier: Natural Language :: English
Classifier: Programming Language :: Python :: 2
Classifier: Programming Language :: Python :: 2.7
Classifier: Programming Language :: Python :: 3
Classifier: Programming Language :: Python :: 3.3
Classifier: Programming Language :: Python :: 3.4
